AUTHORS.rst
CONTRIBUTING.rst
HISTORY.rst
LICENSE
MANIFEST.in
README.rst
setup.cfg
setup.py
djangocms_spa/__init__.py
djangocms_spa/apps.py
djangocms_spa/cms_plugins.py
djangocms_spa/content_helpers.py
djangocms_spa/decorators.py
djangocms_spa/fields.py
djangocms_spa/form_helpers.py
djangocms_spa/forms.py
djangocms_spa/json_encoders.py
djangocms_spa/models.py
djangocms_spa/partial_callbacks.py
djangocms_spa/renderer.py
djangocms_spa/renderer_pool.py
djangocms_spa/serializers.py
djangocms_spa/urls.py
djangocms_spa/utils.py
djangocms_spa/views.py
djangocms_spa.egg-info/PKG-INFO
djangocms_spa.egg-info/SOURCES.txt
djangocms_spa.egg-info/dependency_links.txt
djangocms_spa.egg-info/not-zip-safe
djangocms_spa.egg-info/requires.txt
djangocms_spa.egg-info/top_level.txt
djangocms_spa/templates/djangocms_spa/empty.html
djangocms_spa/templatetags/__init__.py
djangocms_spa/templatetags/app_version_tags.py