Metadata-Version: 1.1
Name: djangocms-spa
Version: 0.1.27
Summary: Run your django CMS project as a single-page application (SPA)
Home-page: https://github.com/dreipol/djangocms-spa
Author: dreipol GmbH
Author-email: dev@dreipol.ch
License: MIT
Keywords: djangocms-spa
Platform: UNKNOWN
Classifier: Development Status :: 3 - Alpha
Classifier: Framework :: Django
Classifier: Framework :: Django :: 2.2
Classifier: Intended Audience :: Developers
Classifier: License :: OSI Approved :: BSD License
Classifier: Natural Language :: English
Classifier: Programming Language :: Python :: 3
Classifier: Programming Language :: Python :: 3.7
Classifier: Programming Language :: Python :: 3.8
